Workbook

Sheet Instructions
B2: SR&ED Activity Log — Template Guide
B3: Use this workbook to log your team's R&D activity. Upload to TaxLift and we'll include it in your SR&ED credit estimate.
B5: WHAT IS SR&ED?
C6: SR&ED (Scientific Research & Experimental Development) is Canada's largest R&D tax incentive program, administered by the CRA. CCPCs can claim up to 35% of eligible expenditures as a refundable credit.
B8: WHO SHOULD FILL THIS IN?
C9: Engineering leads, tech leads, or anyone who can describe what your team built and why it was technically uncertain.
B11: HOW TO USE THIS TEMPLATE
B12: Step 1 | C12: Go to the 'Activity Log' sheet. Each row = one development activity or story.
B13: Step 2 | C13: Fill in Date, Type, Module, Title, and Description columns first.
B14: Step 3 | C14: For each row, set 'SR&ED Eligible?' to Yes / No / Partial.
B15: Step 4 | C15: Fill in Hours Spent and Developer Role — these drive the credit estimate.
B16: Step 5 | C16: For eligible rows, briefly describe the Technological Uncertainty (see below).
B17: Step 6 | C17: Save the file and upload it at taxlift.ai/dashboard.
B19: COLUMN GUIDE
B20: Date | C20: Date the work was completed (YYYY-MM-DD). Use the actual completion date, not commit date.
B21: Type | C21: Feature | Bug Fix | Security | Research | Experiment | Infrastructure | Documentation
B22: Module / Area | C22: The part of your product this work belongs to (e.g. API, Authentication, ML Pipeline, UI).
B23: Title | C23: Short description — same as your ticket/commit title is fine (max ~80 chars).
B24: Description | C24: What you built and why. More detail here = stronger CRA narrative. 1–3 sentences minimum.
B25: Developer Role | C25: Developer | Senior Developer | Architect | QA Engineer | ML Engineer | Product
B26: Hours Spent | C26: Total hours your team spent on this activity. Estimate is fine — CRA allows ±15%.
B27: SR&ED Eligible? | C27: Yes = clearly eligible | Partial = part of the work qualifies | No = routine work
B28: Technological Uncertainty | C28: Required for eligible rows. What did you NOT know how to do before starting? Example: 'Unsure whether transformer embeddings would generalise to short code snippets under 10 tokens.'
B29: Impact | C29: Critical | High | Medium | Low — your team's assessment of business impact.
B31: WHAT MAKES WORK SRED-ELIGIBLE?
C32: ✓ You didn't know in advance whether the approach would work
C33: ✓ You investigated a scientific or technological uncertainty
C34: ✓ The work involved systematic investigation (experiment, testing, iteration)
C35: ✗ Routine bug fixes with known solutions are NOT eligible
C36: ✗ Standard integration work (REST APIs, off-the-shelf libraries) is NOT eligible
B38: IMPORTANT NOTES
C39: • Do not delete columns or rename headers — TaxLift's parser uses exact column names.
C40: • You can add rows for each sprint, month, or ticket — whatever is easiest for your team.
C41: • If you are unsure about eligibility, mark it 'Partial' and our system will flag it for CPA review.
C42: • This template covers developer time only. Materials, subcontractors, and overhead can be added via your CPA.

Sheet Activity Log
A1: SR&ED Activity Log
A2: Company: [Your Company Name] Fiscal Year: [YYYY] Prepared by: [Name] Date: [YYYY-MM-DD]
A3: Date | B3: Type | C3: Module / Area | D3: Title | E3: Description | F3: Developer Role | G3: Hours Spent | H3: SR&ED Eligible? | I3: Technological Uncertainty | J3: Impact
A4: 2024-06-15 | B4: Research | C4: ML Pipeline | D4: Evaluate embedding models for domain classification | E4: Compared three transformer architectures (BERT-base, RoBERTa, DeBERTa) for short-text classification on proprietary dataset. No prior benchmarks exist for this domain. | F4: Senior Developer | G4: 40 | H4: Yes | I4: Unknown whether pre-trained LLMs would transfer to highly domain-specific short text without fine-tuning. Domain vocabulary substantially differs from training corpora. | J4: High
A5: 2024-06-14 | B5: Experiment | C5: ML Pipeline | D5: Test tokenisation strategies for mixed code/prose inputs | E5: Investigated whether a single tokeniser could handle mixed code-prose inputs without accuracy loss. Prior work assumed homogeneous input type. | F5: ML Engineer | G5: 32 | H5: Yes | I5: Unclear whether shared tokenisation degrades performance on code tokens with low corpus frequency. No published results for this mixed-input regime. | J5: High
A6: 2024-06-12 | B6: Feature | C6: API | D6: Adaptive rate-limiting with per-tenant exponential backoff | E6: Built per-tenant rate limiter with exponential backoff. Standard libraries lacked per-tenant granularity; custom sliding-window algorithm required. | F6: Senior Developer | G6: 28 | H6: Partial | I6: Uncertain whether a sliding-window algorithm would remain accurate under burst traffic without adding unacceptable latency. | J6: Medium
A7: 2024-06-10 | B7: Infrastructure | C7: Data Pipeline | D7: Fault-tolerant CDC stream from legacy PostgreSQL | E7: Set up change-data-capture from a legacy PostgreSQL instance with no native replication slot support. Required custom WAL-level parsing. | F7: Architect | G7: 52 | H7: Yes | I7: Unclear whether WAL-level parsing would be reliable across minor PostgreSQL versions without vendor support documentation. | J7: High
A8: 2024-06-08 | B8: Security | C8: Authentication | D8: Zero-trust session model for multi-region deployment | E8: Investigated PASETO vs JWT for stateless sessions in a multi-region active-active setup. Focused on clock-skew handling and replay detection. | F8: Senior Developer | G8: 24 | H8: Yes | I8: No established guidance for clock-skew tolerance in active-active session validation without a central session store. | J8: High
A9: 2024-06-05 | B9: Feature | C9: Search | D9: Semantic search over structured + unstructured data | E9: Developed hybrid BM25 + dense vector index for mixed structured/unstructured queries. Off-the-shelf solutions degraded significantly on structured filters. | F9: ML Engineer | G9: 60 | H9: Yes | I9: Unknown whether vector similarity could be combined with relational filters without recall degradation at scale. | J9: High
A10: 2024-06-03 | B10: Bug Fix | C10: API | D10: Fix memory leak in WebSocket connection pool | E10: Traced gradual memory growth in the WS pool under sustained load. Root cause was unreleased event listeners on reconnect cycles. | F10: Developer | G10: 8 | H10: No | J10: Medium
A11: 2024-05-31 | B11: Research | C11: Data Pipeline | D11: Incremental model retraining on live production streams | E11: Benchmarked full retrain vs. continual learning on live production data stream. Evaluated catastrophic forgetting risk under distribution shift. | F11: ML Engineer | G11: 44 | H11: Yes | I11: Uncertainty whether continual fine-tuning on streaming data causes catastrophic forgetting without explicit replay mechanisms. | J11: High
A12: 2024-05-28 | B12: Feature | C12: UI | D12: Real-time collaborative editing with CRDT merge | E12: Implemented CRDT-based conflict resolution for simultaneous multi-user edits. Operational transforms not viable at this document schema complexity. | F12: Senior Developer | G12: 56 | H12: Partial | I12: Uncertain whether CRDT merge semantics preserve document integrity under concurrent structural (not just text) edits. | J12: High
A13: 2024-05-24 | B13: Experiment | C13: ML Pipeline | D13: Few-shot classification with 3–5 labelled examples | E13: Tested whether GPT-4 style few-shot prompting could replace a fine-tuned classifier for low-resource categories in production. | F13: ML Engineer | G13: 36 | H13: Yes | I13: No reliable method to predict few-shot accuracy at under 5 examples for highly imbalanced classes in this domain. | J13: Medium
A14: 2024-05-20 | B14: Infrastructure | C14: DevOps | D14: Blue-green deployment with zero-downtime schema migration | E14: Designed a blue-green pipeline handling schema migrations mid-cutover without read locks on a 200GB live table. | F14: Architect | G14: 38 | H14: Partial | I14: Unclear whether online schema migration tooling (gh-ost) handles trigger-heavy schemas without replication lag amplification. | J14: High
A15: 2024-05-16 | B15: Feature | C15: Billing | D15: Sub-minute usage metering for accurate per-call billing | E15: Built metering system tracking API usage at sub-minute resolution. Existing solutions had a 5-minute floor, making per-call billing inaccurate. | F15: Developer | G15: 16 | H15: No | J15: Medium
A16: 2024-05-12 | B16: Research | C16: Search | D16: Benchmark ANN libraries for production workload | E16: Benchmarked FAISS, Annoy, and ScaNN on recall vs. latency for our dimensionality and update frequency requirements. | F16: Senior Developer | G16: 30 | H16: Yes | I16: No published benchmarks matched our update frequency (>500 writes/sec) with high dimensionality (1536-dim) vectors. | J16: High
A17: 2024-05-08 | B17: Security | C17: Infrastructure | D17: Custom seccomp profiles for container runtime hardening | E17: Authored custom seccomp profiles restricting syscalls to minimum required set. Default Docker profiles insufficient for compliance posture. | F17: Architect | G17: 18 | H17: Partial | I17: Uncertain whether restricting to minimal syscall set would remain stable across kernel minor versions and container runtimes. | J17: Low
A18: 2024-05-04 | B18: Feature | C18: API | D18: Idempotency key system for distributed payment processing | E18: Implemented server-side idempotency keys with Redis-backed deduplication window to prevent double-charge under retry storms. | F18: Senior Developer | G18: 32 | H18: Yes | I18: Uncertain whether a Redis TTL-based deduplication window remains consistent under split-brain scenarios without distributed locking. | J18: High
A55: TOTALS | G55: =SUMIF(G4:G54,">0",G4:G54) -> 514 | H55: =COUNTIF(H4:H54,"Yes")&" Yes / "&COUNTIF(H4:H54,"Partial")&" Partial" -> 9 Yes / 4 Partial

Sheet Credit Estimate
B1: SR&ED Credit Estimate
B2: Based on hours logged in Activity Log — TaxLift will refine this estimate after CPA review.
B4: A. Assumptions (yellow = your inputs)
C5: Developer | D5: Senior Developer | E5: Architect / ML
B6: Avg annual salary (CAD) | C6: 90000 | D6: 115000 | E6: 145000
B7: Overhead rate | C7: 0.2 | D7: 0.2 | E7: 0.2
B8: Annual working hours | C8: 1800 | D8: 1800 | E8: 1800
B10: B. Hours from Activity Log (linked — do not edit)
C11: Yes (eligible) | D11: Partial (50%) | E11: Total hours
B12: Developer | C12: =SUMPRODUCT(('Activity Log'!G$4:G$200)*('Activity Log'!F$4:F$200="Developer")*('Activity Log'!H$4:H$200="Yes")) -> 0 | D12: =SUMPRODUCT(('Activity Log'!G$4:G$200)*('Activity Log'!F$4:F$200="Developer")*('Activity Log'!H$4:H$200="Partial"))*0.5 -> 0 | E12: =SUMPRODUCT(('Activity Log'!G$4:G$200)*('Activity Log'!F$4:F$200="Developer")) -> 24
B13: Senior Developer | C13: =SUMPRODUCT(('Activity Log'!G$4:G$200)*('Activity Log'!F$4:F$200="Senior Developer")*('Activity Log'!H$4:H$200="Yes")) -> 126 | D13: =SUMPRODUCT(('Activity Log'!G$4:G$200)*('Activity Log'!F$4:F$200="Senior Developer")*('Activity Log'!H$4:H$200="Partial"))*0.5 -> 42 | E13: =SUMPRODUCT(('Activity Log'!G$4:G$200)*('Activity Log'!F$4:F$200="Senior Developer")) -> 210
B14: Architect | C14: =SUMPRODUCT(('Activity Log'!G$4:G$200)*('Activity Log'!F$4:F$200="Architect")*('Activity Log'!H$4:H$200="Yes")) -> 52 | D14: =SUMPRODUCT(('Activity Log'!G$4:G$200)*('Activity Log'!F$4:F$200="Architect")*('Activity Log'!H$4:H$200="Partial"))*0.5 -> 28 | E14: =SUMPRODUCT(('Activity Log'!G$4:G$200)*('Activity Log'!F$4:F$200="Architect")) -> 108
B15: ML Engineer | C15: =SUMPRODUCT(('Activity Log'!G$4:G$200)*('Activity Log'!F$4:F$200="ML Engineer")*('Activity Log'!H$4:H$200="Yes")) -> 172 | D15: =SUMPRODUCT(('Activity Log'!G$4:G$200)*('Activity Log'!F$4:F$200="ML Engineer")*('Activity Log'!H$4:H$200="Partial"))*0.5 -> 0 | E15: =SUMPRODUCT(('Activity Log'!G$4:G$200)*('Activity Log'!F$4:F$200="ML Engineer")) -> 172
B16: QA Engineer | C16: =SUMPRODUCT(('Activity Log'!G$4:G$200)*('Activity Log'!F$4:F$200="QA Engineer")*('Activity Log'!H$4:H$200="Yes")) -> 0 | D16: =SUMPRODUCT(('Activity Log'!G$4:G$200)*('Activity Log'!F$4:F$200="QA Engineer")*('Activity Log'!H$4:H$200="Partial"))*0.5 -> 0 | E16: =SUMPRODUCT(('Activity Log'!G$4:G$200)*('Activity Log'!F$4:F$200="QA Engineer")) -> 0
B17: Product | C17: =SUMPRODUCT(('Activity Log'!G$4:G$200)*('Activity Log'!F$4:F$200="Product")*('Activity Log'!H$4:H$200="Yes")) -> 0 | D17: =SUMPRODUCT(('Activity Log'!G$4:G$200)*('Activity Log'!F$4:F$200="Product")*('Activity Log'!H$4:H$200="Partial"))*0.5 -> 0 | E17: =SUMPRODUCT(('Activity Log'!G$4:G$200)*('Activity Log'!F$4:F$200="Product")) -> 0
B18: TOTAL ELIGIBLE HOURS | C18: =SUM(C12:C17) -> 350 | D18: =SUM(D12:D17) -> 70 | E18: =SUM(E12:E17) -> 514
B20: C. Eligible Expenditures (CAD)
C21: Developer | D21: Senior Developer | E21: Architect / ML
B22: Hourly rate (salary ÷ hrs/yr) | C22: =C6/C8 -> 50 | D22: =D6/D8 -> 63.888889 | E22: =E6/E8 -> 80.555556
B23: Eligible dev time (Yes) | C23: =C12*(C6/C8) -> 0 | D23: =D13*(D6/D8) -> 2683.3333 | E23: =E14*(E6/E8) -> 8700
B24: Eligible dev time (Partial × 50%) | C24: =C13*(C6/C8) -> 6300 | D24: =D14*(D6/D8) -> 1788.8889 | E24: =E15*(E6/E8) -> 13855.556
B25: Overhead on eligible time (20%) | C25: =(C23+C24)*C7 -> 1260 | D25: =(D23+D24)*D7 -> 894.44444 | E25: =(E23+E24)*E7 -> 4511.1111
B26: Total eligible expenditure | C26: =C23+C24+C25 -> 7560 | D26: =D23+D24+D25 -> 5366.6667 | E26: =E23+E24+E25 -> 27066.667
B28: D. SR&ED Credit Summary
B29: Total eligible expenditure (all roles) | E29: =C26+D26+E26 -> 39993.333
B30: Federal SR&ED credit rate (CCPC ≤ $3M income) | E30: 35%
B31: Provincial credit rate (Ontario example — adjust for your province) | E31: 8%
B32: Federal SR&ED refundable credit | E32: =C29*C30 -> 0
B33: Provincial SR&ED refundable credit | E33: =C29*C31 -> 0
B34: TOTAL ESTIMATED SR&ED CREDIT | E34: =C32+C33 -> 0
B36: ⚠ This estimate is indicative only. Final SR&ED claims must be prepared and certified by a qualified CPA. TaxLift automates data extraction and narrative generation — your CPA signs off on the T661.
